odooghost/__init__.py
odooghost/__main__.py
odooghost/cli/__init__.py
odooghost/cli/config.py
odooghost/cli/root.py
odooghost/cli/stack/__init__.py
odooghost/cli/stack/config.py
odooghost/cli/stack/data.py
odooghost/cli/stack/root.py
odooghost/config/__init__.py
odooghost/config/addons.py
odooghost/config/app.py
odooghost/config/dependency.py
odooghost/config/service.py
odooghost/config/stack.py
odooghost/constant.py
odooghost/container.py
odooghost/context.py
odooghost/exceptions.py
odooghost/filters.py
odooghost/git.py
odooghost/logger.py
odooghost/renderer.py
odooghost/services/__init__.py
odooghost/services/base.py
odooghost/services/db.py
odooghost/services/mail.py
odooghost/services/odoo/__init__.py
odooghost/services/odoo/addons.py
odooghost/services/odoo/service.py
odooghost/stack.py
odooghost/templates/Dockerfile.j2
odooghost/types.py
odooghost/utils/__init__.py
odooghost/utils/autocomplete.py
odooghost/utils/exec.py
odooghost/utils/misc.py
odooghost/utils/progress_stream.py
odooghost/utils/signals.py
odooghost/utils/stream.py
odooghost/utils/sync_to_async.py
odooghost/web/__init__.py
odooghost/web/api/__init__.py
odooghost/web/api/mutation/__init__.py
odooghost/web/api/mutation/stack.py
odooghost/web/api/query/__init__.py
odooghost/web/api/query/dashboard.py
odooghost/web/api/query/stack.py
odooghost/web/api/schema.py
odooghost/web/api/schema_types.py
odooghost/web/api/subscription.py
odooghost/web/application.py
odooghost/web/dist/android-chrome-192x192.png
odooghost/web/dist/android-chrome-512x512.png
odooghost/web/dist/apple-touch-icon.png
odooghost/web/dist/favicon-16x16.png
odooghost/web/dist/favicon-32x32.png
odooghost/web/dist/favicon.ico
odooghost/web/dist/index.html
odooghost/web/dist/logo.svg
odooghost/web/dist/site.webmanifest
odooghost-0.15.0.dist-info/LICENSE
odooghost-0.15.0.dist-info/METADATA
odooghost-0.15.0.dist-info/WHEEL
odooghost-0.15.0.dist-info/entry_points.txt
odooghost-0.15.0.dist-info/RECORD
