Metadata-Version: 2.1
Name: odooghost
Version: 0.15.0
Summary: Odoo developpement made easy
Home-page: https://remyz17.github.io/odooghost/
License: MIT
Author: Remy Zulauff
Author-email: remy.zulauff@gmail.com
Requires-Python: >=3.9,<4.0
Classifier: License :: OSI Approved :: MIT License
Classifier: Programming Language :: Python :: 3
Classifier: Programming Language :: Python :: 3.9
Classifier: Programming Language :: Python :: 3.10
Classifier: Programming Language :: Python :: 3.11
Classifier: Programming Language :: Python :: 3.12
Classifier: Programming Language :: Python :: 3.13
Requires-Dist: docker (==7.1.0)
Requires-Dist: dockerpty (>=0.4.1,<0.5.0)
Requires-Dist: gitpython (>=3.1.40,<4.0.0)
Requires-Dist: giturlparse (>=0.12.0,<0.13.0)
Requires-Dist: jinja2 (>=3.1.2,<4.0.0)
Requires-Dist: loguru (>=0.7.0,<0.8.0)
Requires-Dist: pydantic[dotenv] (>=2.0.3,<3.0.0)
Requires-Dist: pyyaml (>=6.0.1,<7.0.0)
Requires-Dist: strawberry-graphql[asgi] (>=0.205.0,<0.206.0)
Requires-Dist: typer[all] (>=0.9.0,<0.10.0)
Requires-Dist: uvicorn[standard] (>=0.23.2,<0.24.0)
Project-URL: Repository, https://github.com/remyz17/odooghost
